ndex2/__init__.py
ndex2/client.py
ndex2/niceCxInterface.py
ndex2/nice_cx_network.py
ndex2/tests/Create_without_panda_helper.py
ndex2/tests/Tester.py
ndex2/tests/__init__.py
ndex2/tests/run_matrix.py
ndex2/tests/scratch1.py
ndex2/tests/scratch_learning.py
ndex2/tests/test_citations.py
ndex2/tests/test_cx_writer.py
ndex2/tests/test_data_types.py
ndex2/tests/test_diffusion.py
ndex2/tests/test_load_network.py
ndex2/tests/test_loading_by_aspects.py
ndex2/tests/test_ndex2_cecilia.py
ndex2/tests/test_ndex2_client.py
ndex2/tests/test_ndex_nodes_attr.py
ndex2/tests/test_network_editing.py
ndex2/tests/test_numpy_array_to_cx.py
ndex2/tests/test_regression.py
ndex2/tests/test_search.py
ndex2_dev-2.0.0.6.dist-info/DESCRIPTION.rst
ndex2_dev-2.0.0.6.dist-info/METADATA
ndex2_dev-2.0.0.6.dist-info/RECORD
ndex2_dev-2.0.0.6.dist-info/WHEEL
ndex2_dev-2.0.0.6.dist-info/metadata.json
ndex2_dev-2.0.0.6.dist-info/top_level.txt
ndex2cx/__init__.py
ndex2cx/nice_cx_builder.py
ndex2cx/parallelCX.py
