Metadata-Version: 2.0
Name: ndex2-dev
Version: 2.0.0.6
Summary: Nice CX Python includes a client and a data model.
Home-page: http://www.ndexbio.org
Author: The NDEx Project
Author-email: contact@ndexbio.org
License: BSD
Keywords: network analysis biology
Platform: UNKNOWN
Classifier: Development Status :: 3 - Alpha
Classifier: Intended Audience :: Science/Research
Classifier: Topic :: Scientific/Engineering :: Information Analysis
Classifier: Topic :: Scientific/Engineering :: Bio-Informatics
Classifier: Topic :: Scientific/Engineering :: Medical Science Apps.
Classifier: License :: OSI Approved :: BSD License
Classifier: Programming Language :: Python :: 3.6
Provides-Extra: 
Requires-Dist: six
Requires-Dist: ijson
Requires-Dist: requests
Requires-Dist: requests-toolbelt
Requires-Dist: networkx
Requires-Dist: urllib3 (>=1.16)
Requires-Dist: pandas
Requires-Dist: enum34
Requires-Dist: pysolr
Requires-Dist: neo4jrestclient
Requires-Dist: enum; python_version == "2.6" or python_version == "2.7"
